[
    {
        "username": "johanbigdickhezbollah",
        "password": "johan",
        "favorite_games": [
            {
                "name": "Stardew Valley",
                "image": "https:\/\/media.rawg.io\/media\/games\/713\/713269608dc8f2f40f5a670a14b2de94.jpg"
            }
        ],
        "id": 2
    },
    {
        "username": "aaaa",
        "password": "aaaa",
        "favorite_games": [
            {
                "name": "Grand Theft Auto V",
                "image": "https:\/\/media.rawg.io\/media\/games\/456\/456dea5e1c7e3cd07060c14e96612001.jpg"
            }
        ],
        "id": 4
    },
    {
        "username": "eqqq",
        "password": "eqqq",
        "favorite_games": [],
        "id": 5
    },
    {
        "username": "adamcheaib",
        "password": "adamcheaib",
        "favorite_games": [
            {
                "name": "Grand Theft Auto V",
                "image": "https:\/\/media.rawg.io\/media\/games\/456\/456dea5e1c7e3cd07060c14e96612001.jpg"
            },
            {
                "name": "Tomb Raider (2013)",
                "image": "https:\/\/media.rawg.io\/media\/games\/021\/021c4e21a1824d2526f925eff6324653.jpg"
            }
        ],
        "id": 1,
        "pending": [],
        "friends": [
            "eeee",
            "eqqq",
            "aaaa"
        ]
    },
    {
        "username": "eeee",
        "password": "eeee",
        "favorite_games": [
            {
                "name": "Gwent: The Witcher Card Game",
                "image": "https:\/\/media.rawg.io\/media\/games\/742\/7424c1f7d0a8da9ae29cd866f985698b.jpg"
            },
            {
                "name": "Faeria",
                "image": "https:\/\/media.rawg.io\/media\/games\/f64\/f6429c7e6e66c178fde186977ea1af75.jpg"
            },
            {
                "name": "Grand Theft Auto V",
                "image": "https:\/\/media.rawg.io\/media\/games\/456\/456dea5e1c7e3cd07060c14e96612001.jpg"
            },
            {
                "name": "Tomb Raider (2013)",
                "image": "https:\/\/media.rawg.io\/media\/games\/021\/021c4e21a1824d2526f925eff6324653.jpg"
            },
            {
                "name": "BioShock Infinite",
                "image": "https:\/\/media.rawg.io\/media\/games\/fc1\/fc1307a2774506b5bd65d7e8424664a7.jpg"
            },
            {
                "name": "The Elder Scrolls V: Skyrim",
                "image": "https:\/\/media.rawg.io\/media\/games\/7cf\/7cfc9220b401b7a300e409e539c9afd5.jpg"
            }
        ],
        "id": 3,
        "pending": [
            "calle",
            "calle",
            "calle",
            "calle"
        ],
        "friends": [
            "adamcheaib"
        ]
    },
    {
        "username": "calle",
        "password": "calle",
        "favorite_games": [],
        "id": 6,
        "favorite_game_images": "elden-ring-new-header-mobile.jpg",
        "profile_picture": "guts.jpg",
        "banner_picture": "Vagabond-2.avif",
        "profile_comments": [
            {
                "message": "ge",
                "timestamp": "2023-05-22 14:21:32"
            },
            {
                "message": "ge",
                "timestamp": "2023-05-22 14:21:53"
            },
            {
                "message": "gr",
                "timestamp": "2023-05-23 09:52:22"
            }
        ]
    }
]